pyElizaChatbotClient/__init__.py
pyElizaChatbotClient/__main__.py
pyElizaChatbotClient/pyEliza.cfg
pyElizaChatbotClient/pyEliza.py
pyElizaChatbotClient/eliza/__init__.py
pyElizaChatbotClient/eliza/eliza.py
pyElizaChatbotClient/eliza/eliza_traveller.py
pyElizaChatbotClient/test/__init__.py
pyElizaChatbotClient/test/pyElizaChatbotClient.py
pyElizaChatbotClient/utils/__init__.py
pyElizaChatbotClient/utils/createXMLfromJson.py
pyElizaChatbotClient-0.1.6.dist-info/DESCRIPTION.rst
pyElizaChatbotClient-0.1.6.dist-info/METADATA
pyElizaChatbotClient-0.1.6.dist-info/RECORD
pyElizaChatbotClient-0.1.6.dist-info/WHEEL
pyElizaChatbotClient-0.1.6.dist-info/metadata.json
pyElizaChatbotClient-0.1.6.dist-info/pbr.json
pyElizaChatbotClient-0.1.6.dist-info/top_level.txt
pyIeshaChatbotClient/__init__.py
pyIeshaChatbotClient/__main__.py
pyIeshaChatbotClient/pyClient.py
pyIeshaChatbotClient/chatbot/__init__.py
pyIeshaChatbotClient/chatbot/iesha.py
pyIeshaChatbotClient/test/__init__.py
pyIeshaChatbotClient/test/pyChatbotClient.py
pyIeshaChatbotClient/utils/__init__.py
pyIeshaChatbotClient/utils/createXMLfromJson.py
pyRudeChatbotClient/__init__.py
pyRudeChatbotClient/__main__.py
pyRudeChatbotClient/pyClient.py
pyRudeChatbotClient/chatbot/__init__.py
pyRudeChatbotClient/chatbot/rude.py
pyRudeChatbotClient/test/__init__.py
pyRudeChatbotClient/test/pyChatbotClient.py
pyRudeChatbotClient/utils/__init__.py
pyRudeChatbotClient/utils/createXMLfromJson.py
pyZenChatbotClient/__init__.py
pyZenChatbotClient/__main__.py
pyZenChatbotClient/pyClient.py
pyZenChatbotClient/chatbot/__init__.py
pyZenChatbotClient/chatbot/zenmaster.py
pyZenChatbotClient/test/__init__.py
pyZenChatbotClient/test/pyChatbotClient.py
pyZenChatbotClient/utils/__init__.py
pyZenChatbotClient/utils/createXMLfromJson.py
