Metadata-Version: 2.0
Name: pyElizaChatbotClient
Version: 0.1.6
Summary: Basic stand-alone/websocket client for using in the Re-WoChat Shared task.
Home-page: http://workshop.colips.org/re-wochat/
Author: Luis Fernando D'Haro
Author-email: luisdhe@i2r.a-star.edu.sg
License: LICENSE.txt
Keywords: chatbots eliza re-wochat shared-task
Platform: UNKNOWN
Requires-Dist: autobahn[twisted] (>=0.11.0)
Requires-Dist: future (>=0.15.2)
Requires-Dist: nltk (>=3.1)
Requires-Dist: petl (>=1.1.0)
Requires-Dist: twisted (>=15.5.0)
